esp_bool_parser/__init__.py
esp_bool_parser/bool_parser.py
esp_bool_parser/constants.py
esp_bool_parser/py.typed
esp_bool_parser/soc_header.py
esp_bool_parser/utils.py
esp_bool_parser-0.2.1.dist-info/licenses/LICENSE
esp_bool_parser-0.2.1.dist-info/WHEEL
esp_bool_parser-0.2.1.dist-info/METADATA
esp_bool_parser-0.2.1.dist-info/RECORD
