Metadata-Version: 2.4
Name: esp-bool-parser
Version: 0.2.1
Summary: Tools for building ESP-IDF related apps.
Author-email: Fu Hanxi <fuhanxi@espressif.com>
Requires-Python: >=3.7
Classifier: Development Status :: 5 - Production/Stable
Classifier: License :: OSI Approved :: Apache Software License
Classifier: Programming Language :: Python :: 3.7
Classifier: Programming Language :: Python :: 3.8
Classifier: Programming Language :: Python :: 3.9
Classifier: Programming Language :: Python :: 3.10
Classifier: Programming Language :: Python :: 3.11
Classifier: Programming Language :: Python :: 3.12
Classifier: Programming Language :: Python :: 3.13
Classifier: Programming Language :: Python :: 3.14
License-File: LICENSE
Requires-Dist: pyparsing
Requires-Dist: packaging
Requires-Dist: sphinx ; extra == "doc"
Requires-Dist: sphinx-rtd-theme ; extra == "doc"
Requires-Dist: sphinx_copybutton ; extra == "doc"
Requires-Dist: myst-parser ; extra == "doc"
Requires-Dist: sphinxcontrib-mermaid ; extra == "doc"
Requires-Dist: sphinx-argparse ; extra == "doc"
Requires-Dist: sphinx-tabs ; extra == "doc"
Requires-Dist: pytest ; extra == "test"
Requires-Dist: pytest-cov ; extra == "test"
Project-URL: changelog, https://github.com/espressif/esp-bool-parsers/blob/main/CHANGELOG.md
Project-URL: documentation, https://docs.espressif.com/projects/esp-bool-parser
Project-URL: homepage, https://github.com/espressif/esp-bool-parser
Project-URL: repository, https://github.com/espressif/esp-bool-parser
Provides-Extra: doc
Provides-Extra: test
